async_websocket_client/__init__.py
async_websocket_client/ws.py
micropython_async_websocket_client-0.3.4.dist-info/licenses/LICENSE
micropython_async_websocket_client-0.3.4.dist-info/METADATA
micropython_async_websocket_client-0.3.4.dist-info/WHEEL
micropython_async_websocket_client-0.3.4.dist-info/top_level.txt
micropython_async_websocket_client-0.3.4.dist-info/RECORD
