Metadata-Version: 2.4
Name: micropython-async_websocket_client
Version: 0.3.4
Summary: Asynchronous websocket client for ESP32 controller.
Author-email: Vladimir Badashkin <bd_postbox1@mail.ru>
License:                                  Apache License
Project-URL: repository, https://github.com/Vovaman/micropython_async_websocket_client
Project-URL: documentation, https://github.com/Vovaman/example_async_websocket/
Classifier: Programming Language :: Python :: 3
Classifier: License :: OSI Approved :: Apache Software License
Classifier: Operating System :: OS Independent
Requires-Python: >=3.10
License-File: LICENSE
Dynamic: license-file
